decode/keycode_to_notes.sv
`define keycode_1 8'h16
`define keycode_2 8'h1e
`define keycode_3 8'h26
`define keycode_4 8'h25
`define keycode_5 8'h2e
`define keycode_6 8'h36
`define keycode_7 8'h3d
`define keycode_8 8'h3e
`define keycode_9 8'h46
`define keycode_0 8'h45
`define keycode_minus 8'h4e
`define keycode_plus 8'h55

`define keycode_num_1 8'h69
`define keycode_num_2 8'h72
`define keycode_num_3 8'h7a
`define keycode_num_4 8'h6b
`define keycode_num_5 8'h73
`define keycode_num_6 8'h74
`define keycode_num_7 8'h6c
`define keycode_num_8 8'h75
`define keycode_num_9 8'h7d
`define keycode_num_0 8'h7c
`define keycode_num_enter 8'h5a


`define keycode_a 8'h1c
`define keycode_b 8'h32
`define keycode_c 8'h21
`define keycode_d 8'h23
`define keycode_e 8'h24
`define keycode_f 8'h2b
`define keycode_g 8'h34
`define keycode_h 8'h33
`define keycode_i 8'h43
`define keycode_j 8'h3b
`define keycode_k 8'h42
`define keycode_l 8'h4b
`define keycode_m 8'h3a
`define keycode_n 8'h31
`define keycode_o 8'h44
`define keycode_p 8'h4d
`define keycode_q 8'h15
`define keycode_r 8'h2d
`define keycode_s 8'h1b
`define keycode_t 8'h2c
`define keycode_u 8'h3c
`define keycode_v 8'h2a
`define keycode_w 8'h1d
`define keycode_x 8'h22
`define keycode_y 8'h35
`define keycode_z 8'h1a
`define keycode_semicolon 8'h4c
`define keycode_quote 8'h52
`define keycode_comma 8'h41
`define keycode_dot 8'h49


`define keycode_space 8'h29
`define keycode_enter 8'h5a
`define keycode_ctrl 8'h14
`define keycode_shift 8'h12
`define keycode_del 8'h66

`define keycode_f1 8'h05
`define keycode_f2 8'h06
`define keycode_f3 8'h04
`define keycode_f4 8'h0c
`define keycode_f5 8'h03
`define keycode_f6 8'h0b
`define keycode_f7 8'h83
`define keycode_f8 8'h0a
`define keycode_f9 8'h01
`define keycode_f10 8'h09
`define keycode_f11 8'h78
`define keycode_f12 8'h07

`define keycode_esc 8'h76
`define keycode_tab 8'h0d
`define keycode_caps 8'h58

`define keycode_up 8'h75
`define keycode_down 8'h72
`define keycode_left 8'h6b
`define keycode_right 8'h74


`define note_C 4'd1
`define note_Cs 4'd2
`define note_D 4'd3
`define note_Ds 4'd4
`define note_E 4'd5
`define note_F 4'd6
`define note_Fs 4'd7
`define note_G 4'd8
`define note_Gs 4'd9
`define note_A 4'd10
`define note_As 4'd11
`define note_B 4'd12


`define MAX_NOTES_NUM 16
module keycode_to_notes(
    input clk,
    input reset,
    input [15:0] keycode,
    input start,
    output reg [7:0] notes [0:`MAX_NOTES_NUM - 1],   // [6:4]: zone, [3:0]: semi-tone, [7]: reserved
                                                    // eg. D4: zone=4, semi-tone=3, notes=0100_0011
    output reg [4:0] note_num = 0
    );
    reg [1:0] note_map [2:7][1:12]; // [zone][semi-tone] 0: key-up, 1: key-down

    wire [7:0] keycode_h8;
    wire [7:0] keycode_l8;
    assign keycode_h8 = keycode[15:8];
    assign keycode_l8 = keycode[7:0];
    

    reg [3:0] chord_mark;

    reg [4:0] note_idx;
    always @(posedge clk) begin

        if (reset) begin
            for (int i = 2; i <= 7; i = i + 1) begin
                    for (int j = 1; j <= 12; j = j + 1) begin
                        note_map[i][j] = 0;
                    end
            end
        end else begin
            if (start) begin
                if (!(keycode_h8 == 8'hF0)) begin // key-down
                    case (keycode_l8)
                        // single
                        `keycode_a: note_map[4][1] = 1;
                        `keycode_w: note_map[4][2] = 1;
                        `keycode_s: note_map[4][3] = 1;
                        `keycode_e: note_map[4][4] = 1;
                        `keycode_d: note_map[4][5] = 1;
                        `keycode_f: note_map[4][6] = 1;
                        `keycode_t: note_map[4][7] = 1;
                        `keycode_g: note_map[4][8] = 1;
                        `keycode_y: note_map[4][9] = 1;
                        `keycode_h: note_map[4][10] = 1;
                        `keycode_u: note_map[4][11] = 1;
                        `keycode_j: note_map[4][12] = 1;
                        `keycode_k: note_map[5][1] = 1;
                        `keycode_o: note_map[5][2] = 1;
                        `keycode_l: note_map[5][3] = 1;
                        `keycode_p: note_map[5][4] = 1;
                        `keycode_semicolon: note_map[5][5] = 1;
                        `keycode_quote: note_map[5][6] = 1;

                        `keycode_1: note_map[5][1] = 1;
                        `keycode_2: note_map[5][3] = 1;
                        `keycode_3: note_map[5][5] = 1;
                        `keycode_4: note_map[5][6] = 1;
                        `keycode_5: note_map[5][8] = 1;
                        `keycode_6: note_map[5][10] = 1;
                        `keycode_7: note_map[5][12] = 1;
                        `keycode_8: note_map[6][1] = 1;
                        `keycode_9: note_map[6][3] = 1;
                        `keycode_0: note_map[6][5] = 1;

                        `keycode_z: note_map[3][1] = 1;
                        `keycode_x: note_map[3][3] = 1;
                        `keycode_c: note_map[3][5] = 1;
                        `keycode_v: note_map[3][6] = 1;
                        `keycode_b: note_map[3][8] = 1;
                        `keycode_n: note_map[3][10] = 1;
                        `keycode_m: note_map[3][12] = 1;
                        `keycode_comma: note_map[4][1] = 1;
                        `keycode_dot: note_map[4][3] = 1;

                        // chords
                        `keycode_num_1: chord_mark = 1;
                        `keycode_num_2: chord_mark = 2;
                        `keycode_num_3: chord_mark = 3;
                        `keycode_num_4: chord_mark = 4;
                        `keycode_num_5: chord_mark = 5;
                        `keycode_num_6: chord_mark = 6;
                        `keycode_num_7: chord_mark = 7;

                        default: ;
                    endcase
                end else begin
                    case (keycode_l8)
                        // single
                        `keycode_a: note_map[4][1] = 0;
                        `keycode_w: note_map[4][2] = 0;
                        `keycode_s: note_map[4][3] = 0;
                        `keycode_e: note_map[4][4] = 0;
                        `keycode_d: note_map[4][5] = 0;
                        `keycode_f: note_map[4][6] = 0;
                        `keycode_t: note_map[4][7] = 0;
                        `keycode_g: note_map[4][8] = 0;
                        `keycode_y: note_map[4][9] = 0;
                        `keycode_h: note_map[4][10] = 0;
                        `keycode_u: note_map[4][11] = 0;
                        `keycode_j: note_map[4][12] = 0;
                        `keycode_k: note_map[5][1] = 0;
                        `keycode_o: note_map[5][2] = 0;
                        `keycode_l: note_map[5][3] = 0;
                        `keycode_p: note_map[5][4] = 0;
                        `keycode_semicolon: note_map[5][5] = 0;
                        `keycode_quote: note_map[5][6] = 0;

                        `keycode_1: note_map[5][1] = 0;
                        `keycode_2: note_map[5][3] = 0;
                        `keycode_3: note_map[5][5] = 0;
                        `keycode_4: note_map[5][6] = 0;
                        `keycode_5: note_map[5][8] = 0;
                        `keycode_6: note_map[5][10] = 0;
                        `keycode_7: note_map[5][12] = 0;
                        `keycode_8: note_map[6][1] = 0;
                        `keycode_9: note_map[6][3] = 0;
                        `keycode_0: note_map[6][5] = 0;

                        `keycode_z: note_map[3][1] = 0;
                        `keycode_x: note_map[3][3] = 0;
                        `keycode_c: note_map[3][5] = 0;
                        `keycode_v: note_map[3][6] = 0;
                        `keycode_b: note_map[3][8] = 0;
                        `keycode_n: note_map[3][10] = 0;
                        `keycode_m: note_map[3][12] = 0;
                        `keycode_comma: note_map[4][1] = 0;
                        `keycode_dot: note_map[4][3] = 0;

                        // chords
                        `keycode_num_1: chord_mark = 0;
                        `keycode_num_2: chord_mark = 0;
                        `keycode_num_3: chord_mark = 0;
                        `keycode_num_4: chord_mark = 0;
                        `keycode_num_5: chord_mark = 0;
                        `keycode_num_6: chord_mark = 0;
                        `keycode_num_7: chord_mark = 0;
                        
                        default: ;
                    endcase
                end
                
            end
        end 
    end


    wire clk_slow;
    clock_generator #(
        .FREQUENCY_i(300),
        .FREQENCY_o(1)
    ) clock_generator (
        .clk_i(clk),
        .clk_o(clk_slow)
    );


    always @(posedge clk_slow) begin


        if (reset) begin

            for (int i = 0; i < `MAX_NOTES_NUM; i = i + 1) begin
                notes[i] = 0;
            end

        end else begin

                note_idx = 0;

                for (int i = 2; i <= 7; i = i + 1) begin //  zone
                    for (int j = 1; j <= 12; j = j + 1) begin //  semi-tone
                        if (note_map[i][j] > 0) begin
                            if (note_idx < 10) begin
                                notes[note_idx] = {1'b0, i[2:0], j[3:0]};
                                note_idx = note_idx + 1;
                            end
                        end
                    end
                end

                note_num = note_idx;

                if (note_idx < 10) begin
                    if (note_idx <= 9) notes[9] = 0;
                    if (note_idx <= 8) notes[8] = 0;
                    if (note_idx <= 7) notes[7] = 0;
                    if (note_idx <= 6) notes[6] = 0;
                    if (note_idx <= 5) notes[5] = 0;
                    if (note_idx <= 4) notes[4] = 0;
                    if (note_idx <= 3) notes[3] = 0;
                    if (note_idx <= 2) notes[2] = 0;
                    if (note_idx <= 1) notes[1] = 0;
                    if (note_idx <= 0) notes[0] = 0;
                end


                // chords
                case (chord_mark)
                    0: begin
                        notes[10] <= 0;
                        notes[11] <= 0;
                        notes[12] <= 0;
                        notes[13] <= 0;
                        notes[14] <= 0;
                        notes[15] <= 0;
                    end

                    1: begin
                        notes[10] <= {1'b0, 3'd3, `note_C};
                        notes[11] <= {1'b0, 3'd3, `note_G};
                        notes[12] <= {1'b0, 3'd4, `note_C};
                        notes[13] <= {1'b0, 3'd4, `note_E};
                        notes[14] <= 0;
                        notes[15] <= 0;
                    end

                    2: begin
                        notes[10] <= {1'b0, 3'd3, `note_D};
                        notes[11] <= {1'b0, 3'd3, `note_A};
                        notes[12] <= {1'b0, 3'd4, `note_D};
                        notes[13] <= {1'b0, 3'd4, `note_F};
                        notes[14] <= 0;
                        notes[15] <= 0;
                    end

                    3: begin
                        notes[10] <= {1'b0, 3'd3, `note_E};
                        notes[11] <= {1'b0, 3'd3, `note_G};
                        notes[12] <= {1'b0, 3'd3, `note_B};
                        notes[13] <= {1'b0, 3'd4, `note_E};
                        notes[14] <= 0;
                        notes[15] <= 0;
                    end

                    4: begin
                        notes[10] <= {1'b0, 3'd3, `note_F};
                        notes[11] <= {1'b0, 3'd3, `note_A};
                        notes[12] <= {1'b0, 3'd4, `note_C};
                        notes[13] <= {1'b0, 3'd4, `note_F};
                        notes[14] <= 0;
                        notes[15] <= 0;
                    end

                    5: begin
                        notes[10] <= {1'b0, 3'd3, `note_G};
                        notes[11] <= {1'b0, 3'd3, `note_B};
                        notes[12] <= {1'b0, 3'd4, `note_D};
                        notes[13] <= {1'b0, 3'd4, `note_G};
                        notes[14] <= 0;
                        notes[15] <= {1'b0, 2'd2, `note_G};
                    end

                    6: begin
                        notes[10] <= {1'b0, 3'd3, `note_A};
                        notes[11] <= {1'b0, 3'd3, `note_C};
                        notes[12] <= {1'b0, 3'd4, `note_E};
                        notes[13] <= 0;
                        notes[14] <= 0;
                        notes[15] <= 0;
                    end

                    7: begin
                        notes[10] <= {1'b0, 3'd3, `note_B};
                        notes[11] <= {1'b0, 3'd3, `note_D};
                        notes[12] <= {1'b0, 3'd4, `note_F};
                        notes[13] <= 0;
                        notes[14] <= 0;
                        notes[15] <= 0;
                    end

                    default: ;
                endcase


        end
    end


endmodule


module clock_generator #(
    parameter real FREQUENCY_i = 100000000, // 1MHz
    parameter real FREQENCY_o = 1 // Hz
) (
    input clk_i,
    output reg clk_o = 0
);

    localparam integer DIV_FACTOR = FREQUENCY_i / (2 * FREQENCY_o);
    reg [$clog2(DIV_FACTOR):0] cnt = 0;

    always @(negedge clk_i) begin
        if (cnt == DIV_FACTOR - 1) begin
            clk_o <= ~clk_o;
            cnt <= 0;
        end else begin
            cnt <= cnt + 1;
        end
    end
    
endmodule

decode/tb_decode.sv
// my testbench template
`timescale 1ps/1ps
`include "keycode_to_notes.sv"

module tb_decode;

    /* iverilog */
    initial begin
        $dumpfile("tb_decode.vcd");
        $dumpvars(0, tb_decode);
    end

    reg reset;
    reg start = 1;
    reg [15:0] keycode;
    wire [7:0] notes [0:`MAX_NOTES_NUM - 1];
    wire [4:0] note_num;


    keycode_to_notes keycode_to_notes(
        .clk(clk),
        .start(start),
        .reset(reset),
        .keycode(keycode),
        .notes(notes),
        .note_num(note_num)
    );


    initial begin
        reset=1; #10
        reset=0;
    end

    //clk
    reg clk = 0;
    always #1 clk = ~clk;


    initial begin
        #15
        keycode = {8'h00, `keycode_a}; #2000;
        keycode = {8'hf0, `keycode_a}; #2000;
        keycode = {8'h00, `keycode_w}; #2000;
        keycode = {8'hf0, `keycode_w}; #2000;

        keycode = {8'h00, `keycode_s}; #2000;
        keycode = {8'h00, `keycode_e}; #2000;
        keycode = {8'hf0, `keycode_s}; #2000;
        keycode = {8'hf0, `keycode_e}; #2000;

        end

    wire [7:0] note0 = notes[0];
    wire [7:0] note1 = notes[1];
    wire [7:0] note2 = notes[2];
    wire [7:0] note3 = notes[3];
    wire [7:0] note4 = notes[4];

    wire C4_d = keycode_to_notes.note_map[4][1];
    wire C4s_d = keycode_to_notes.note_map[4][2];
    wire D4_d = keycode_to_notes.note_map[4][3];


    initial begin
        #30000 $finish;
    end
    
endmodule

decode/tb_decode.vcd
$date
	Sun Dec 29 17:03:24 2024
$end
$version
	Icarus Verilog
$end
$timescale
	1ps
$end
$scope module tb_decode $end
$var wire 8 ! note0 [7:0] $end
$var wire 8 " note1 [7:0] $end
$var wire 8 # note2 [7:0] $end
$var wire 8 $ note3 [7:0] $end
$var wire 8 % note4 [7:0] $end
$var wire 5 & note_num [4:0] $end
$var wire 1 ' D4_d $end
$var wire 1 ( C4s_d $end
$var wire 1 ) C4_d $end
$var reg 1 * clk $end
$var reg 16 + keycode [15:0] $end
$var reg 1 , reset $end
$var reg 1 - start $end
$scope module keycode_to_notes $end
$var wire 1 * clk $end
$var wire 16 . keycode [15:0] $end
$var wire 1 , reset $end
$var wire 1 - start $end
$var wire 8 / keycode_l8 [7:0] $end
$var wire 8 0 keycode_h8 [7:0] $end
$var wire 1 1 clk_slow $end
$var reg 4 2 chord_mark [3:0] $end
$var reg 5 3 note_idx [4:0] $end
$var reg 5 4 note_num [4:0] $end
$scope module clock_generator $end
$var wire 1 * clk_i $end
$var parameter 32 5 DIV_FACTOR $end
$var real 1 6 FREQENCY_o $end
$var real 1 7 FREQUENCY_i $end
$var reg 1 1 clk_o $end
$var reg 9 8 cnt [8:0] $end
$upscope $end
$scope begin $ivl_for_loop0 $end
$var integer 32 9 i [31:0] $end
$scope begin $ivl_for_loop1 $end
$var integer 32 : j [31:0] $end
$upscope $end
$upscope $end
$scope begin $ivl_for_loop2 $end
$var integer 32 ; i [31:0] $end
$upscope $end
$scope begin $ivl_for_loop3 $end
$var integer 32 < i [31:0] $end
$scope begin $ivl_for_loop4 $end
$var integer 32 = j [31:0] $end
$upscope $end
$upscope $end
$upscope $end
$upscope $end
$enddefinitions $end
$comment Show the parameter values. $end
$dumpall
r300 7
r1 6
b10010110 5
$end
#0
$dumpvars
b0 =
b0 <
b0 ;
b0 :
b0 9
b0 8
b0 4
bx 3
bx 2
01
bx 0
bx /
bx .
1-
1,
bx +
0*
x)
x(
x'
b0 &
bx %
bx $
bx #
bx "
bx !
$end
#1
0'
0(
0)
b1101 :
b1000 9
1*
#2
b1 8
0*
#3
b1101 :
b1000 9
1*
#4
b10 8
0*
#5
b1101 :
b1000 9
1*
#6
b11 8
0*
#7
b1101 :
b1000 9
1*
#8
b100 8
0*
#9
b1101 :
b1000 9
1*
#10
b101 8
0*
0,
#11
1*
#12
b110 8
0*
#13
1*
#14
b111 8
0*
#15
1)
b0 0
b11100 /
1*
b11100 +
b11100 .
#16
b1000 8
0*
#17
1*
#18
b1001 8
0*
#19
1*
#20
b1010 8
0*
#21
1*
#22
b1011 8
0*
#23
1*
#24
b1100 8
0*
#25
1*
#26
b1101 8
0*
#27
1*
#28
b1110 8
0*
#29
1*
#30
b1111 8
0*
#31
1*
#32
b10000 8
0*
#33
1*
#34
b10001 8
0*
#35
1*
#36
b10010 8
0*
#37
1*
#38
b10011 8
0*
#39
1*
#40
b10100 8
0*
#41
1*
#42
b10101 8
0*
#43
1*
#44
b10110 8
0*
#45
1*
#46
b10111 8
0*
#47
1*
#48
b11000 8
0*
#49
1*
#50
b11001 8
0*
#51
1*
#52
b11010 8
0*
#53
1*
#54
b11011 8
0*
#55
1*
#56
b11100 8
0*
#57
1*
#58
b11101 8
0*
#59
1*
#60
b11110 8
0*
#61
1*
#62
b11111 8
0*
#63
1*
#64
b100000 8
0*
#65
1*
#66
b100001 8
0*
#67
1*
#68
b100010 8
0*
#69
1*
#70
b100011 8
0*
#71
1*
#72
b100100 8
0*
#73
1*
#74
b100101 8
0*
#75
1*
#76
b100110 8
0*
#77
1*
#78
b100111 8
0*
#79
1*
#80
b101000 8
0*
#81
1*
#82
b101001 8
0*
#83
1*
#84
b101010 8
0*
#85
1*
#86
b101011 8
0*
#87
1*
#88
b101100 8
0*
#89
1*
#90
b101101 8
0*
#91
1*
#92
b101110 8
0*
#93
1*
#94
b101111 8
0*
#95
1*
#96
b110000 8
0*
#97
1*
#98
b110001 8
0*
#99
1*
#100
b110010 8
0*
#101
1*
#102
b110011 8
0*
#103
1*
#104
b110100 8
0*
#105
1*
#106
b110101 8
0*
#107
1*
#108
b110110 8
0*
#109
1*
#110
b110111 8
0*
#111
1*
#112
b111000 8
0*
#113
1*
#114
b111001 8
0*
#115
1*
#116
b111010 8
0*
#117
1*
#118
b111011 8
0*
#119
1*
#120
b111100 8
0*
#121
1*
#122
b111101 8
0*
#123
1*
#124
b111110 8
0*
#125
1*
#126
b111111 8
0*
#127
1*
#128
b1000000 8
0*
#129
1*
#130
b1000001 8
0*
#131
1*
#132
b1000010 8
0*
#133
1*
#134
b1000011 8
0*
#135
1*
#136
b1000100 8
0*
#137
1*
#138
b1000101 8
0*
#139
1*
#140
b1000110 8
0*
#141
1*
#142
b1000111 8
0*
#143
1*
#144
b1001000 8
0*
#145
1*
#146
b1001001 8
0*
#147
1*
#148
b1001010 8
0*
#149
1*
#150
b1001011 8
0*
#151
1*
#152
b1001100 8
0*
#153
1*
#154
b1001101 8
0*
#155
1*
#156
b1001110 8
0*
#157
1*
#158
b1001111 8
0*
#159
1*
#160
b1010000 8
0*
#161
1*
#162
b1010001 8
0*
#163
1*
#164
b1010010 8
0*
#165
1*
#166
b1010011 8
0*
#167
1*
#168
b1010100 8
0*
#169
1*
#170
b1010101 8
0*
#171
1*
#172
b1010110 8
0*
#173
1*
#174
b1010111 8
0*
#175
1*
#176
b1011000 8
0*
#177
1*
#178
b1011001 8
0*
#179
1*
#180
b1011010 8
0*
#181
1*
#182
b1011011 8
0*
#183
1*
#184
b1011100 8
0*
#185
1*
#186
b1011101 8
0*
#187
1*
#188
b1011110 8
0*
#189
1*
#190
b1011111 8
0*
#191
1*
#192
b1100000 8
0*
#193
1*
#194
b1100001 8
0*
#195
1*
#196
b1100010 8
0*
#197
1*
#198
b1100011 8
0*
#199
1*
#200
b1100100 8
0*
#201
1*
#202
b1100101 8
0*
#203
1*
#204
b1100110 8
0*
#205
1*
#206
b1100111 8
0*
#207
1*
#208
b1101000 8
0*
#209
1*
#210
b1101001 8
0*
#211
1*
#212
b1101010 8
0*
#213
1*
#214
b1101011 8
0*
#215
1*
#216
b1101100 8
0*
#217
1*
#218
b1101101 8
0*
#219
1*
#220
b1101110 8
0*
#221
1*
#222
b1101111 8
0*
#223
1*
#224
b1110000 8
0*
#225
1*
#226
b1110001 8
0*
#227
1*
#228
b1110010 8
0*
#229
1*
#230
b1110011 8
0*
#231
1*
#232
b1110100 8
0*
#233
1*
#234
b1110101 8
0*
#235
1*
#236
b1110110 8
0*
#237
1*
#238
b1110111 8
0*
#239
1*
#240
b1111000 8
0*
#241
1*
#242
b1111001 8
0*
#243
1*
#244
b1111010 8
0*
#245
1*
#246
b1111011 8
0*
#247
1*
#248
b1111100 8
0*
#249
1*
#250
b1111101 8
0*
#251
1*
#252
b1111110 8
0*
#253
1*
#254
b1111111 8
0*
#255
1*
#256
b10000000 8
0*
#257
1*
#258
b10000001 8
0*
#259
1*
#260
b10000010 8
0*
#261
1*
#262
b10000011 8
0*
#263
1*
#264
b10000100 8
0*
#265
1*
#266
b10000101 8
0*
#267
1*
#268
b10000110 8
0*
#269
1*
#270
b10000111 8
0*
#271
1*
#272
b10001000 8
0*
#273
1*
#274
b10001001 8
0*
#275
1*
#276
b10001010 8
0*
#277
1*
#278
b10001011 8
0*
#279
1*
#280
b10001100 8
0*
#281
1*
#282
b10001101 8
0*
#283
1*
#284
b10001110 8
0*
#285
1*
#286
b10001111 8
0*
#287
1*
#288
b10010000 8
0*
#289
1*
#290
b10010001 8
0*
#291
1*
#292
b10010010 8
0*
#293
1*
#294
b10010011 8
0*
#295
1*
#296
b10010100 8
0*
#297
1*
#298
b10010101 8
0*
#299
1*
#300
b0 "
b0 #
b0 $
b0 %
b1 &
b1 4
b1000001 !
b1101 =
b1000 <
b1 3
b0 8
11
0*
#301
1*
#302
b1 8
0*
#303
1*
#304
b10 8
0*
#305
1*
#306
b11 8
0*
#307
1*
#308
b100 8
0*
#309
1*
#310
b101 8
0*
#311
1*
#312
b110 8
0*
#313
1*
#314
b111 8
0*
#315
1*
#316
b1000 8
0*
#317
1*
#318
b1001 8
0*
#319
1*
#320
b1010 8
0*
#321
1*
#322
b1011 8
0*
#323
1*
#324
b1100 8
0*
#325
1*
#326
b1101 8
0*
#327
1*
#328
b1110 8
0*
#329
1*
#330
b1111 8
0*
#331
1*
#332
b10000 8
0*
#333
1*
#334
b10001 8
0*
#335
1*
#336
b10010 8
0*
#337
1*
#338
b10011 8
0*
#339
1*
#340
b10100 8
0*
#341
1*
#342
b10101 8
0*
#343
1*
#344
b10110 8
0*
#345
1*
#346
b10111 8
0*
#347
1*
#348
b11000 8
0*
#349
1*
#350
b11001 8
0*
#351
1*
#352
b11010 8
0*
#353
1*
#354
b11011 8
0*
#355
1*
#356
b11100 8
0*
#357
1*
#358
b11101 8
0*
#359
1*
#360
b11110 8
0*
#361
1*
#362
b11111 8
0*
#363
1*
#364
b100000 8
0*
#365
1*
#366
b100001 8
0*
#367
1*
#368
b100010 8
0*
#369
1*
#370
b100011 8
0*
#371
1*
#372
b100100 8
0*
#373
1*
#374
b100101 8
0*
#375
1*
#376
b100110 8
0*
#377
1*
#378
b100111 8
0*
#379
1*
#380
b101000 8
0*
#381
1*
#382
b101001 8
0*
#383
1*
#384
b101010 8
0*
#385
1*
#386
b101011 8
0*
#387
1*
#388
b101100 8
0*
#389
1*
#390
b101101 8
0*
#391
1*
#392
b101110 8
0*
#393
1*
#394
b101111 8
0*
#395
1*
#396
b110000 8
0*
#397
1*
#398
b110001 8
0*
#399
1*
#400
b110010 8
0*
#401
1*
#402
b110011 8
0*
#403
1*
#404
b110100 8
0*
#405
1*
#406
b110101 8
0*
#407
1*
#408
b110110 8
0*
#409
1*
#410
b110111 8
0*
#411
1*
#412
b111000 8
0*
#413
1*
#414
b111001 8
0*
#415
1*
#416
b111010 8
0*
#417
1*
#418
b111011 8
0*
#419
1*
#420
b111100 8
0*
#421
1*
#422
b111101 8
0*
#423
1*
#424
b111110 8
0*
#425
1*
#426
b111111 8
0*
#427
1*
#428
b1000000 8
0*
#429
1*
#430
b1000001 8
0*
#431
1*
#432
b1000010 8
0*
#433
1*
#434
b1000011 8
0*
#435
1*
#436
b1000100 8
0*
#437
1*
#438
b1000101 8
0*
#439
1*
#440
b1000110 8
0*
#441
1*
#442
b1000111 8
0*
#443
1*
#444
b1001000 8
0*
#445
1*
#446
b1001001 8
0*
#447
1*
#448
b1001010 8
0*
#449
1*
#450
b1001011 8
0*
#451
1*
#452
b1001100 8
0*
#453
1*
#454
b1001101 8
0*
#455
1*
#456
b1001110 8
0*
#457
1*
#458
b1001111 8
0*
#459
1*
#460
b1010000 8
0*
#461
1*
#462
b1010001 8
0*
#463
1*
#464
b1010010 8
0*
#465
1*
#466
b1010011 8
0*
#467
1*
#468
b1010100 8
0*
#469
1*
#470
b1010101 8
0*
#471
1*
#472
b1010110 8
0*
#473
1*
#474
b1010111 8
0*
#475
1*
#476
b1011000 8
0*
#477
1*
#478
b1011001 8
0*
#479
1*
#480
b1011010 8
0*
#481
1*
#482
b1011011 8
0*
#483
1*
#484
b1011100 8
0*
#485
1*
#486
b1011101 8
0*
#487
1*
#488
b1011110 8
0*
#489
1*
#490
b1011111 8
0*
#491
1*
#492
b1100000 8
0*
#493
1*
#494
b1100001 8
0*
#495
1*
#496
b1100010 8
0*
#497
1*
#498
b1100011 8
0*
#499
1*
#500
b1100100 8
0*
#501
1*
#502
b1100101 8
0*
#503
1*
#504
b1100110 8
0*
#505
1*
#506
b1100111 8
0*
#507
1*
#508
b1101000 8
0*
#509
1*
#510
b1101001 8
0*
#511
1*
#512
b1101010 8
0*
#513
1*
#514
b1101011 8
0*
#515
1*
#516
b1101100 8
0*
#517
1*
#518
b1101101 8
0*
#519
1*
#520
b1101110 8
0*
#521
1*
#522
b1101111 8
0*
#523
1*
#524
b1110000 8
0*
#525
1*
#526
b1110001 8
0*
#527
1*
#528
b1110010 8
0*
#529
1*
#530
b1110011 8
0*
#531
1*
#532
b1110100 8
0*
#533
1*
#534
b1110101 8
0*
#535
1*
#536
b1110110 8
0*
#537
1*
#538
b1110111 8
0*
#539
1*
#540
b1111000 8
0*
#541
1*
#542
b1111001 8
0*
#543
1*
#544
b1111010 8
0*
#545
1*
#546
b1111011 8
0*
#547
1*
#548
b1111100 8
0*
#549
1*
#550
b1111101 8
0*
#551
1*
#552
b1111110 8
0*
#553
1*
#554
b1111111 8
0*
#555
1*
#556
b10000000 8
0*
#557
1*
#558
b10000001 8
0*
#559
1*
#560
b10000010 8
0*
#561
1*
#562
b10000011 8
0*
#563
1*
#564
b10000100 8
0*
#565
1*
#566
b10000101 8
0*
#567
1*
#568
b10000110 8
0*
#569
1*
#570
b10000111 8
0*
#571
1*
#572
b10001000 8
0*
#573
1*
#574
b10001001 8
0*
#575
1*
#576
b10001010 8
0*
#577
1*
#578
b10001011 8
0*
#579
1*
#580
b10001100 8
0*
#581
1*
#582
b10001101 8
0*
#583
1*
#584
b10001110 8
0*
#585
1*
#586
b10001111 8
0*
#587
1*
#588
b10010000 8
0*
#589
1*
#590
b10010001 8
0*
#591
1*
#592
b10010010 8
0*
#593
1*
#594
b10010011 8
0*
#595
1*
#596
b10010100 8
0*
#597
1*
#598
b10010101 8
0*
#599
1*
#600
b0 8
01
0*
#601
1*
#602
b1 8
0*
#603
1*
#604
b10 8
0*
#605
1*
#606
b11 8
0*
#607
1*
#608
b100 8
0*
#609
1*
#610
b101 8
0*
#611
1*
#612
b110 8
0*
#613
1*
#614
b111 8
0*
#615
1*
#616
b1000 8
0*
#617
1*
#618
b1001 8
0*
#619
1*
#620
b1010 8
0*
#621
1*
#622
b1011 8
0*
#623
1*
#624
b1100 8
0*
#625
1*
#626
b1101 8
0*
#627
1*
#628
b1110 8
0*
#629
1*
#630
b1111 8
0*
#631
1*
#632
b10000 8
0*
#633
1*
#634
b10001 8
0*
#635
1*
#636
b10010 8
0*
#637
1*
#638
b10011 8
0*
#639
1*
#640
b10100 8
0*
#641
1*
#642
b10101 8
0*
#643
1*
#644
b10110 8
0*
#645
1*
#646
b10111 8
0*
#647
1*
#648
b11000 8
0*
#649
1*
#650
b11001 8
0*
#651
1*
#652
b11010 8
0*
#653
1*
#654
b11011 8
0*
#655
1*
#656
b11100 8
0*
#657
1*
#658
b11101 8
0*
#659
1*
#660
b11110 8
0*
#661
1*
#662
b11111 8
0*
#663
1*
#664
b100000 8
0*
#665
1*
#666
b100001 8
0*
#667
1*
#668
b100010 8
0*
#669
1*
#670
b100011 8
0*
#671
1*
#672
b100100 8
0*
#673
1*
#674
b100101 8
0*
#675
1*
#676
b100110 8
0*
#677
1*
#678
b100111 8
0*
#679
1*
#680
b101000 8
0*
#681
1*
#682
b101001 8
0*
#683
1*
#684
b101010 8
0*
#685
1*
#686
b101011 8
0*
#687
1*
#688
b101100 8
0*
#689
1*
#690
b101101 8
0*
#691
1*
#692
b101110 8
0*
#693
1*
#694
b101111 8
0*
#695
1*
#696
b110000 8
0*
#697
1*
#698
b110001 8
0*
#699
1*
#700
b110010 8
0*
#701
1*
#702
b110011 8
0*
#703
1*
#704
b110100 8
0*
#705
1*
#706
b110101 8
0*
#707
1*
#708
b110110 8
0*
#709
1*
#710
b110111 8
0*
#711
1*
#712
b111000 8
0*
#713
1*
#714
b111001 8
0*
#715
1*
#716
b111010 8
0*
#717
1*
#718
b111011 8
0*
#719
1*
#720
b111100 8
0*
#721
1*
#722
b111101 8
0*
#723
1*
#724
b111110 8
0*
#725
1*
#726
b111111 8
0*
#727
1*
#728
b1000000 8
0*
#729
1*
#730
b1000001 8
0*
#731
1*
#732
b1000010 8
0*
#733
1*
#734
b1000011 8
0*
#735
1*
#736
b1000100 8
0*
#737
1*
#738
b1000101 8
0*
#739
1*
#740
b1000110 8
0*
#741
1*
#742
b1000111 8
0*
#743
1*
#744
b1001000 8
0*
#745
1*
#746
b1001001 8
0*
#747
1*
#748
b1001010 8
0*
#749
1*
#750
b1001011 8
0*
#751
1*
#752
b1001100 8
0*
#753
1*
#754
b1001101 8
0*
#755
1*
#756
b1001110 8
0*
#757
1*
#758
b1001111 8
0*
#759
1*
#760
b1010000 8
0*
#761
1*
#762
b1010001 8
0*
#763
1*
#764
b1010010 8
0*
#765
1*
#766
b1010011 8
0*
#767
1*
#768
b1010100 8
0*
#769
1*
#770
b1010101 8
0*
#771
1*
#772
b1010110 8
0*
#773
1*
#774
b1010111 8
0*
#775
1*
#776
b1011000 8
0*
#777
1*
#778
b1011001 8
0*
#779
1*
#780
b1011010 8
0*
#781
1*
#782
b1011011 8
0*
#783
1*
#784
b1011100 8
0*
#785
1*
#786
b1011101 8
0*
#787
1*
#788
b1011110 8
0*
#789
1*
#790
b1011111 8
0*
#791
1*
#792
b1100000 8
0*
#793
1*
#794
b1100001 8
0*
#795
1*
#796
b1100010 8
0*
#797
1*
#798
b1100011 8
0*
#799
1*
#800
b1100100 8
0*
#801
1*
